LICENSE
MANIFEST.in
README.rst
setup.cfg
setup.py
yahoo_fantasy_api/__init__.py
yahoo_fantasy_api/game.py
yahoo_fantasy_api/league.py
yahoo_fantasy_api/oauth2_logger.py
yahoo_fantasy_api/team.py
yahoo_fantasy_api/utils.py
yahoo_fantasy_api/yhandler.py
yahoo_fantasy_api.egg-info/PKG-INFO
yahoo_fantasy_api.egg-info/SOURCES.txt
yahoo_fantasy_api.egg-info/dependency_links.txt
yahoo_fantasy_api.egg-info/not-zip-safe
yahoo_fantasy_api.egg-info/requires.txt
yahoo_fantasy_api.egg-info/top_level.txt
yahoo_fantasy_api/scripts/yfa_draft_results
yahoo_fantasy_api/scripts/yfa_init_oauth_env
yahoo_fantasy_api/scripts/yfa_league
yahoo_fantasy_api/scripts/yfa_team