Metadata-Version: 2.1
Name: yahoo-fantasy-api
Version: 2.8.0
Summary: Python bindings to access the Yahoo! Fantasy APIs
Home-page: http://github.com/spilchen/yahoo_fantasy_api
Author: Matt Spilchen
Author-email: matt.spilchen@gmail.com
License: MIT
Classifier: Development Status :: 4 - Beta
Classifier: Intended Audience :: Developers
Classifier: License :: OSI Approved :: MIT License
Classifier: Programming Language :: Python :: 3.7
Requires-Python: >=3
License-File: LICENSE
